Kyber_Polar_Codes/Kyber.py
Kyber_Polar_Codes/Repetition_code.py
Kyber_Polar_Codes/__init__.py
KyberPC-0.0.2.dist-info/METADATA
KyberPC-0.0.2.dist-info/WHEEL
KyberPC-0.0.2.dist-info/top_level.txt
KyberPC-0.0.2.dist-info/RECORD
