Metadata-Version: 2.1
Name: KyberPC
Version: 0.0.2
Summary: Kyber with Polar Codes
Home-page: UNKNOWN
Author: Jason-Papa
Author-email: iasonvas@gmail.com
License: UNKNOWN
Keywords: python,Kyber,Error Correction,Polar Codes,Kyber with Polar Codes
Platform: UNKNOWN
Classifier: Development Status :: 1 - Planning
Classifier: Intended Audience :: Developers
Classifier: Programming Language :: Python :: 3
Classifier: Operating System :: Microsoft :: Windows
Requires-Dist: numpy
Requires-Dist: matplotlib
